{"nodes": [{"id": "c_users_nassir_desktop_hospital_flow_scripts_init_db_py", "label": "init_db.py", "file_type": "code", "source_file": "C:\\Users\\Nassir\\Desktop\\hospital_flow\\scripts\\init_db.py", "source_location": "L1"}, {"id": "scripts_init_db_rationale_1", "label": "Initialize the database: create all tables.  Usage:     venv\\Scripts\\python.exe", "file_type": "rationale", "source_file": "C:\\Users\\Nassir\\Desktop\\hospital_flow\\scripts\\init_db.py", "source_location": "L1"}], "edges": [{"source": "c_users_nassir_desktop_hospital_flow_scripts_init_db_py", "target": "app_core_database", "relation": "imports_from", "context": "import", "confidence": "EXTRACTED", "source_file": "C:\\Users\\Nassir\\Desktop\\hospital_flow\\scripts\\init_db.py", "source_location": "L6", "weight": 1.0}, {"source": "scripts_init_db_rationale_1", "target": "c_users_nassir_desktop_hospital_flow_scripts_init_db_py", "relation": "rationale_for", "confidence": "EXTRACTED", "source_file": "C:\\Users\\Nassir\\Desktop\\hospital_flow\\scripts\\init_db.py", "source_location": "L1", "weight": 1.0}], "raw_calls": []}