{"nodes": [{"id": "c_users_nassir_desktop_hospital_flow_services_billing_service_app_events_subscriber_py", "label": "subscriber.py", "file_type": "code", "source_file": "C:\\Users\\Nassir\\Desktop\\hospital_flow\\services\\billing-service\\app\\events\\subscriber.py", "source_location": "L1"}, {"id": "events_subscriber_handle_visit_created", "label": "handle_visit_created()", "file_type": "code", "source_file": "C:\\Users\\Nassir\\Desktop\\hospital_flow\\services\\billing-service\\app\\events\\subscriber.py", "source_location": "L5"}, {"id": "str", "label": "str", "file_type": "code", "source_file": "C:\\Users\\Nassir\\Desktop\\hospital_flow\\services\\billing-service\\app\\events\\subscriber.py", "source_location": "L5"}, {"id": "events_subscriber_handle_drug_dispensed", "label": "handle_drug_dispensed()", "file_type": "code", "source_file": "C:\\Users\\Nassir\\Desktop\\hospital_flow\\services\\billing-service\\app\\events\\subscriber.py", "source_location": "L9"}, {"id": "events_subscriber_handle_patient_admitted", "label": "handle_patient_admitted()", "file_type": "code", "source_file": "C:\\Users\\Nassir\\Desktop\\hospital_flow\\services\\billing-service\\app\\events\\subscriber.py", "source_location": "L13"}, {"id": "events_subscriber_handle_patient_discharged", "label": "handle_patient_discharged()", "file_type": "code", "source_file": "C:\\Users\\Nassir\\Desktop\\hospital_flow\\services\\billing-service\\app\\events\\subscriber.py", "source_location": "L17"}, {"id": "events_subscriber_dispatch", "label": "_dispatch()", "file_type": "code", "source_file": "C:\\Users\\Nassir\\Desktop\\hospital_flow\\services\\billing-service\\app\\events\\subscriber.py", "source_location": "L21"}, {"id": "events_subscriber_start_subscriber", "label": "start_subscriber()", "file_type": "code", "source_file": "C:\\Users\\Nassir\\Desktop\\hospital_flow\\services\\billing-service\\app\\events\\subscriber.py", "source_location": "L31"}, {"id": "events_subscriber_rationale_6", "label": "Stub: process visit.created event.", "file_type": "rationale", "source_file": "C:\\Users\\Nassir\\Desktop\\hospital_flow\\services\\billing-service\\app\\events\\subscriber.py", "source_location": "L6"}, {"id": "events_subscriber_rationale_10", "label": "Stub: process drug.dispensed event.", "file_type": "rationale", "source_file": "C:\\Users\\Nassir\\Desktop\\hospital_flow\\services\\billing-service\\app\\events\\subscriber.py", "source_location": "L10"}, {"id": "events_subscriber_rationale_14", "label": "Stub: process patient.admitted event.", "file_type": "rationale", "source_file": "C:\\Users\\Nassir\\Desktop\\hospital_flow\\services\\billing-service\\app\\events\\subscriber.py", "source_location": "L14"}, {"id": "events_subscriber_rationale_18", "label": "Stub: process patient.discharged event.", "file_type": "rationale", "source_file": "C:\\Users\\Nassir\\Desktop\\hospital_flow\\services\\billing-service\\app\\events\\subscriber.py", "source_location": "L18"}], "edges": [{"source": "c_users_nassir_desktop_hospital_flow_services_billing_service_app_events_subscriber_py", "target": "app_messaging_subscriber", "relation": "imports_from", "context": "import", "confidence": "EXTRACTED", "source_file": "C:\\Users\\Nassir\\Desktop\\hospital_flow\\services\\billing-service\\app\\events\\subscriber.py", "source_location": "L3", "weight": 1.0}, {"source": "c_users_nassir_desktop_hospital_flow_services_billing_service_app_events_subscriber_py", "target": "events_subscriber_handle_visit_created", "relation": "contains", "confidence": "EXTRACTED", "source_file": "C:\\Users\\Nassir\\Desktop\\hospital_flow\\services\\billing-service\\app\\events\\subscriber.py", "source_location": "L5", "weight": 1.0}, {"source": "events_subscriber_handle_visit_created", "target": "str", "relation": "references", "context": "parameter_type", "confidence": "EXTRACTED", "source_file": "C:\\Users\\Nassir\\Desktop\\hospital_flow\\services\\billing-service\\app\\events\\subscriber.py", "source_location": "L5", "weight": 1.0}, {"source": "events_subscriber_handle_visit_created", "target": "str", "relation": "references", "context": "parameter_type", "confidence": "EXTRACTED", "source_file": "C:\\Users\\Nassir\\Desktop\\hospital_flow\\services\\billing-service\\app\\events\\subscriber.py", "source_location": "L5", "weight": 1.0}, {"source": "c_users_nassir_desktop_hospital_flow_services_billing_service_app_events_subscriber_py", "target": "events_subscriber_handle_drug_dispensed", "relation": "contains", "confidence": "EXTRACTED", "source_file": "C:\\Users\\Nassir\\Desktop\\hospital_flow\\services\\billing-service\\app\\events\\subscriber.py", "source_location": "L9", "weight": 1.0}, {"source": "events_subscriber_handle_drug_dispensed", "target": "str", "relation": "references", "context": "parameter_type", "confidence": "EXTRACTED", "source_file": "C:\\Users\\Nassir\\Desktop\\hospital_flow\\services\\billing-service\\app\\events\\subscriber.py", "source_location": "L9", "weight": 1.0}, {"source": "events_subscriber_handle_drug_dispensed", "target": "str", "relation": "references", "context": "parameter_type", "confidence": "EXTRACTED", "source_file": "C:\\Users\\Nassir\\Desktop\\hospital_flow\\services\\billing-service\\app\\events\\subscriber.py", "source_location": "L9", "weight": 1.0}, {"source": "c_users_nassir_desktop_hospital_flow_services_billing_service_app_events_subscriber_py", "target": "events_subscriber_handle_patient_admitted", "relation": "contains", "confidence": "EXTRACTED", "source_file": "C:\\Users\\Nassir\\Desktop\\hospital_flow\\services\\billing-service\\app\\events\\subscriber.py", "source_location": "L13", "weight": 1.0}, {"source": "events_subscriber_handle_patient_admitted", "target": "str", "relation": "references", "context": "parameter_type", "confidence": "EXTRACTED", "source_file": "C:\\Users\\Nassir\\Desktop\\hospital_flow\\services\\billing-service\\app\\events\\subscriber.py", "source_location": "L13", "weight": 1.0}, {"source": "events_subscriber_handle_patient_admitted", "target": "str", "relation": "references", "context": "parameter_type", "confidence": "EXTRACTED", "source_file": "C:\\Users\\Nassir\\Desktop\\hospital_flow\\services\\billing-service\\app\\events\\subscriber.py", "source_location": "L13", "weight": 1.0}, {"source": "c_users_nassir_desktop_hospital_flow_services_billing_service_app_events_subscriber_py", "target": "events_subscriber_handle_patient_discharged", "relation": "contains", "confidence": "EXTRACTED", "source_file": "C:\\Users\\Nassir\\Desktop\\hospital_flow\\services\\billing-service\\app\\events\\subscriber.py", "source_location": "L17", "weight": 1.0}, {"source": "events_subscriber_handle_patient_discharged", "target": "str", "relation": "references", "context": "parameter_type", "confidence": "EXTRACTED", "source_file": "C:\\Users\\Nassir\\Desktop\\hospital_flow\\services\\billing-service\\app\\events\\subscriber.py", "source_location": "L17", "weight": 1.0}, {"source": "events_subscriber_handle_patient_discharged", "target": "str", "relation": "references", "context": "parameter_type", "confidence": "EXTRACTED", "source_file": "C:\\Users\\Nassir\\Desktop\\hospital_flow\\services\\billing-service\\app\\events\\subscriber.py", "source_location": "L17", "weight": 1.0}, {"source": "c_users_nassir_desktop_hospital_flow_services_billing_service_app_events_subscriber_py", "target": "events_subscriber_dispatch", "relation": "contains", "confidence": "EXTRACTED", "source_file": "C:\\Users\\Nassir\\Desktop\\hospital_flow\\services\\billing-service\\app\\events\\subscriber.py", "source_location": "L21", "weight": 1.0}, {"source": "events_subscriber_dispatch", "target": "str", "relation": "references", "context": "parameter_type", "confidence": "EXTRACTED", "source_file": "C:\\Users\\Nassir\\Desktop\\hospital_flow\\services\\billing-service\\app\\events\\subscriber.py", "source_location": "L21", "weight": 1.0}, {"source": "c_users_nassir_desktop_hospital_flow_services_billing_service_app_events_subscriber_py", "target": "events_subscriber_start_subscriber", "relation": "contains", "confidence": "EXTRACTED", "source_file": "C:\\Users\\Nassir\\Desktop\\hospital_flow\\services\\billing-service\\app\\events\\subscriber.py", "source_location": "L31", "weight": 1.0}, {"source": "events_subscriber_dispatch", "target": "events_subscriber_handle_visit_created", "relation": "calls", "context": "call", "confidence": "EXTRACTED", "source_file": "C:\\Users\\Nassir\\Desktop\\hospital_flow\\services\\billing-service\\app\\events\\subscriber.py", "source_location": "L23", "weight": 1.0}, {"source": "events_subscriber_dispatch", "target": "events_subscriber_handle_drug_dispensed", "relation": "calls", "context": "call", "confidence": "EXTRACTED", "source_file": "C:\\Users\\Nassir\\Desktop\\hospital_flow\\services\\billing-service\\app\\events\\subscriber.py", "source_location": "L25", "weight": 1.0}, {"source": "events_subscriber_dispatch", "target": "events_subscriber_handle_patient_admitted", "relation": "calls", "context": "call", "confidence": "EXTRACTED", "source_file": "C:\\Users\\Nassir\\Desktop\\hospital_flow\\services\\billing-service\\app\\events\\subscriber.py", "source_location": "L27", "weight": 1.0}, {"source": "events_subscriber_dispatch", "target": "events_subscriber_handle_patient_discharged", "relation": "calls", "context": "call", "confidence": "EXTRACTED", "source_file": "C:\\Users\\Nassir\\Desktop\\hospital_flow\\services\\billing-service\\app\\events\\subscriber.py", "source_location": "L29", "weight": 1.0}, {"source": "events_subscriber_rationale_6", "target": "events_subscriber_handle_visit_created", "relation": "rationale_for", "confidence": "EXTRACTED", "source_file": "C:\\Users\\Nassir\\Desktop\\hospital_flow\\services\\billing-service\\app\\events\\subscriber.py", "source_location": "L6", "weight": 1.0}, {"source": "events_subscriber_rationale_10", "target": "events_subscriber_handle_drug_dispensed", "relation": "rationale_for", "confidence": "EXTRACTED", "source_file": "C:\\Users\\Nassir\\Desktop\\hospital_flow\\services\\billing-service\\app\\events\\subscriber.py", "source_location": "L10", "weight": 1.0}, {"source": "events_subscriber_rationale_14", "target": "events_subscriber_handle_patient_admitted", "relation": "rationale_for", "confidence": "EXTRACTED", "source_file": "C:\\Users\\Nassir\\Desktop\\hospital_flow\\services\\billing-service\\app\\events\\subscriber.py", "source_location": "L14", "weight": 1.0}, {"source": "events_subscriber_rationale_18", "target": "events_subscriber_handle_patient_discharged", "relation": "rationale_for", "confidence": "EXTRACTED", "source_file": "C:\\Users\\Nassir\\Desktop\\hospital_flow\\services\\billing-service\\app\\events\\subscriber.py", "source_location": "L18", "weight": 1.0}], "raw_calls": [{"caller_nid": "events_subscriber_start_subscriber", "callee": "start_consumer", "is_member_call": false, "source_file": "C:\\Users\\Nassir\\Desktop\\hospital_flow\\services\\billing-service\\app\\events\\subscriber.py", "source_location": "L32"}]}